{
  "project_info": {
    "project_number": "806192057437",
    "firebase_url": "https://signin-6d4a4.firebaseio.com",
    "project_id": "signin-6d4a4",
    "storage_bucket": "signin-6d4a4.appspot.com"
  },
  "client": [
    {
      "client_info": {
        "mobilesdk_app_id": "1:806192057437:android:af33c60253b405287cd1b4",
        "android_client_info": {
          "package_name": "com.example.loginsignup"
        }
      },
      "oauth_client": [
        {
          "client_id": "806192057437-ep376v6re142havbconuripg09fev5ub.apps.googleusercontent.com",
          "client_type": 1,
          "android_info": {
            "package_name": "com.example.loginsignup",
            "certificate_hash": "518e910fd16fbda04d84b9cc0bdb011e64edc65f"
          }
        },
        {
          "client_id": "806192057437-dong70t9de1506p9dgt8443tkdgvsj08.apps.googleusercontent.com",
          "client_type": 3
        }
      ],
      "api_key": [
        {
          "current_key": "AIzaSyAT382wQZIffUPyQpGvU7bA7wzFgsf84RI"
        }
      ],
      "services": {
        "appinvite_service": {
          "other_platform_oauth_client": [
            {
              "client_id": "806192057437-dong70t9de1506p9dgt8443tkdgvsj08.apps.googleusercontent.com",
              "client_type": 3
            }
          ]
        }
      }
    }
  ],
  "configuration_version": "1"
}